README.md
setup.py
down/__init__.py
down/down
down.egg-info/PKG-INFO
down.egg-info/SOURCES.txt
down.egg-info/dependency_links.txt
down.egg-info/requires.txt
down.egg-info/top_level.txt