Metadata-Version: 2.1
Name: down
Version: 1.0
Summary: A CLI tool to check if a site or a list of sites are down or up
Home-page: https://github.com/sdushantha/down
Author: Siddharth Dushantha
Author-email: siddharth.dushantha@gmail.com
License: UNKNOWN
Platform: UNKNOWN
